tmatrix/CMakeLists.txt
tmatrix/__init__.py
tmatrix/__init__.pyi
tmatrix/_tmatrix.cpython-313-x86_64-linux-musl.so
tmatrix/py.typed
tmatrix/version.py
tmatrix/src/.clang-format
tmatrix/src/Gtensor.cpp
tmatrix/src/TMatrix.hpp
tmatrix/src/TMatrixAPI.hpp
tmatrix/src/TMatrix_porosity.cpp
tmatrix/src/calc_C_eff.cpp
tmatrix/src/calc_C_eff_visco.cpp
tmatrix/src/calc_Kd.cpp
tmatrix/src/calc_Kd_uuvv.cpp
tmatrix/src/calc_Theta.cpp
tmatrix/src/calc_X.cpp
tmatrix/src/calc_Z.cpp
tmatrix/src/calc_isolatedpart.cpp
tmatrix/src/calc_t.cpp
tmatrix/src/calc_td.cpp
tmatrix/src/iso_av_all.cpp
tmatrix/src/iso_average.cpp
tmatrix/src/python.cpp
tmatrix/src/velocity_vti_angles.cpp
tmatrix.libs/libgcc_s-0cd532bd.so.1
tmatrix.libs/libstdc++-5d72f927.so.6.0.33
tmatrix-1.1.5.dist-info/METADATA
tmatrix-1.1.5.dist-info/WHEEL
tmatrix-1.1.5.dist-info/RECORD
tmatrix-1.1.5.dist-info/licenses/LICENSE
tmatrix-1.1.5.dist-info/sboms/auditwheel.cdx.json
