Metadata-Version: 2.2
Name: tmatrix
Version: 1.1.5
Summary: Seismic properties and pore structure of carbonate rocks
Requires-Python: <3.14,>=3.11
Requires-Dist: numpy>=1.26.4
